MANIFEST.in
README.md
README.txt
analytics.md
extracting-analytics-data.md
future_configuration.md
setup.py
avaamo/__init__.py
avaamo/add_document.py
avaamo/agent_intervention.py
avaamo/api.py
avaamo/channel_usage.py
avaamo/cli.py
avaamo/configuration.py
avaamo/conversation_dump.py
avaamo/conversations.py
avaamo/get_conversation.py
avaamo/get_cookies.py
avaamo/insights.py
avaamo/insights_dump.py
avaamo/list_document.py
avaamo/list_documents.py
avaamo/message_api.py
avaamo/messages.py
avaamo/messages2.py
avaamo/result_by_filters.py
avaamo/retrain_document.py
avaamo/send_bot_message.py
avaamo/sessions.py
avaamo/sucessful_responses.py
avaamo/top_intents.py
avaamo/unhandled_messages.py
avaamo/usage_stats.py
avaamo/version.py
avaamo.egg-info/PKG-INFO
avaamo.egg-info/SOURCES.txt
avaamo.egg-info/dependency_links.txt
avaamo.egg-info/entry_points.txt
avaamo.egg-info/requires.txt
avaamo.egg-info/top_level.txt
avaamo/api/__init__.py
avaamo/api/answers.py
avaamo/api/bot_controller.py
avaamo/api/message.py