Metadata-Version: 2.1
Name: avaamo
Version: 0.1.2
Summary: Avaamo API for Python
Home-page: http://github.io/avaamo/avaamo-python
Author: David Gwartney
Author-email: david.gwartney@avaamo.io
License: LICENSE
Platform: UNKNOWN
Classifier: Programming Language :: Python :: 3
Classifier: License :: OSI Approved :: MIT License
Classifier: Operating System :: OS Independent
Requires-Python: >=3.7
